cerebrate_file/__init__.py
cerebrate_file/__main__.py
cerebrate_file/__version__.py
cerebrate_file/api_client.py
cerebrate_file/cerebrate_file.py
cerebrate_file/chunking.py
cerebrate_file/cli.py
cerebrate_file/config.py
cerebrate_file/constants.py
cerebrate_file/continuity.py
cerebrate_file/error_recovery.py
cerebrate_file/file_utils.py
cerebrate_file/models.py
cerebrate_file/prompt_library.py
cerebrate_file/recursive.py
cerebrate_file/tokenizer.py
cerebrate_file/ui.py
cerebrate_file/validators.py
cerebrate_file/prompts/README.md
cerebrate_file/prompts/fix-pdf-extracted-text.xml
cerebrate_file-1.0.31.dist-info/METADATA
cerebrate_file-1.0.31.dist-info/WHEEL
cerebrate_file-1.0.31.dist-info/entry_points.txt
cerebrate_file-1.0.31.dist-info/licenses/LICENSE
cerebrate_file-1.0.31.dist-info/RECORD
